edea/.bandit
edea/__init__.py
edea/_type_utils.py
edea/_utils.py
edea/metadata.py
edea/py.typed
edea/cli/__init__.py
edea/cli/__main__.py
edea/cli/add.py
edea/kicad/__init__.py
edea/kicad/_config.py
edea/kicad/_equality.py
edea/kicad/_fields.py
edea/kicad/_kicad_cli.py
edea/kicad/_parse.py
edea/kicad/_serialize.py
edea/kicad/_str_enum.py
edea/kicad/base.py
edea/kicad/cli_types.py
edea/kicad/color.py
edea/kicad/common.py
edea/kicad/design_rules.py
edea/kicad/is_kicad_expr.py
edea/kicad/number.py
edea/kicad/parser.py
edea/kicad/project.py
edea/kicad/s_expr.py
edea/kicad/schematic_group.py
edea/kicad/serializer.py
edea/kicad/checker/README.md
edea/kicad/checker/__init__.py
edea/kicad/checker/drc.py
edea/kicad/checker/erc.py
edea/kicad/checker/reporter.py
edea/kicad/pcb/__init__.py
edea/kicad/pcb/base.py
edea/kicad/pcb/common.py
edea/kicad/pcb/footprint.py
edea/kicad/pcb/graphics.py
edea/kicad/pcb/layer.py
edea/kicad/schematic/__init__.py
edea/kicad/schematic/base.py
edea/kicad/schematic/shapes.py
edea/kicad/schematic/symbol.py
edea-0.8.4.dist-info/METADATA
edea-0.8.4.dist-info/WHEEL
edea-0.8.4.dist-info/entry_points.txt
edea-0.8.4.dist-info/licenses/LICENSE.md
edea-0.8.4.dist-info/RECORD
